obdio/__init__.py
obdio/encoder.py
obdio/obdio.py
obd_socketio-0.3.4.dist-info/LICENSE
obd_socketio-0.3.4.dist-info/METADATA
obd_socketio-0.3.4.dist-info/WHEEL
obd_socketio-0.3.4.dist-info/top_level.txt
obd_socketio-0.3.4.dist-info/RECORD
