Metadata-Version: 2.1
Name: obd-socketio
Version: 0.3.4
Summary: Expose python-OBD through an async socketio server
Home-page: https://github.com/bgunson/obd-socketio
Author: Bennett Gunson
Author-email: bengunson@gmail.com
Project-URL: Bug Tracker, https://github.com/bgunson/obd-socketio/issues
Classifier: Programming Language :: Python :: 3
Classifier: License :: OSI Approved :: GNU General Public License v2 (GPLv2)
Classifier: Operating System :: OS Independent
Requires-Python: >=3.6
License-File: LICENSE
Requires-Dist: obd
Requires-Dist: python-socketio
Requires-Dist: uvicorn
Requires-Dist: websockets
